Metadata-Version: 2.1
Name: bioniceye
Version: 1.0.0
Summary: A Novel Environment
Home-page: https://github.com/namin-an
Author: Na Min An
Author-email: namin0202@gmail.com
Keywords: environment
